gimodules/__init__.py
gimodules/cloudconnect/__init__.py
gimodules/cloudconnect/authenticate.py
gimodules/cloudconnect/cloud_request.py
gimodules/cloudconnect/exceptions.py
gimodules/cloudconnect/gi_websocket.py
gimodules/cloudconnect/input_handler.py
gimodules/cloudconnect/mysql_connect.py
gimodules/cloudconnect/utils.py
gimodules/domain/__init__.py
gimodules/domain/csv.py
gimodules/domain/data_manipulator.py
gimodules/domain/domain.py
gimodules/visualization/__init__.py
gimodules/visualization/definedplots.py
gimodules-0.3.0.dist-info/licenses/LICENSE
tests/__init__.py
tests/test_websocket.py
gimodules-0.3.0.dist-info/METADATA
gimodules-0.3.0.dist-info/WHEEL
gimodules-0.3.0.dist-info/top_level.txt
gimodules-0.3.0.dist-info/RECORD
