Metadata-Version: 2.4
Name: gimodules
Version: 0.3.0
Summary: Python package providing an interface to the Gantner Instruments Cloud API
Author: Gantner Instruments GmbH
Author-email: 
Keywords: python
Classifier: Development Status :: 1 - Planning
Classifier: Intended Audience :: Developers
Classifier: Programming Language :: Python :: 3.7
Classifier: Programming Language :: Python :: 3.8
Classifier: Programming Language :: Python :: 3.9
Classifier: Programming Language :: Python :: 3.10
Classifier: Programming Language :: Python :: 3.11
Classifier: Programming Language :: Python :: 3.12
Classifier: Operating System :: Unix
Classifier: Operating System :: MacOS :: MacOS X
Classifier: Operating System :: Microsoft :: Windows
Requires-Python: >=3.7
License-File: LICENSE
Requires-Dist: certifi==2022.6.15
Requires-Dist: iniconfig==1.1.1
Requires-Dist: ipython==8.12.3
Requires-Dist: ipywidgets==7.7.1
Requires-Dist: matplotlib~=3.5.2
Requires-Dist: numpy==1.23.1
Requires-Dist: pandas==1.4.3
Requires-Dist: pymysql~=1.0.2
Requires-Dist: python-dotenv==1.0.1
Requires-Dist: python_dateutil==2.8.2
Requires-Dist: pytz==2024.1
Requires-Dist: Requests==2.32.3
Requires-Dist: seaborn~=0.11.2
Requires-Dist: sqlalchemy~=2.0.32
Requires-Dist: websocket_client
Requires-Dist: pytest
Requires-Dist: pipenv
Dynamic: author
Dynamic: classifier
Dynamic: description
Dynamic: description-content-type
Dynamic: keywords
Dynamic: license-file
Dynamic: requires-dist
Dynamic: requires-python
Dynamic: summary
